[ {
  "dataset" : "VINIT",
  "userCode" : "FHFHFH-1234",
  "payment" : null,
  "codeType" : null,
  "name" : "DSFSDFHSDf sdfjSD FSDJF SD",
  "payType" : "E",
  "taxability" : "Taxable/Exclude",
  "eemax" : "99999999998.99",
  "ermax" : "-",
  "aggstatus" : "N/A",
  "limit" : null,
  "lmtfreq" : "0",
  "lmtfreqDisp" : "-",
  "eefreq" : "-",
  "eefreqDisp" : "-",
  "erfreq" : "-",
  "erfreqDisp" : "-",
  "aggRule1" : "0",
  "aggRule2" : "0",
  "effective" : null,
  "rescind" : null
}, {
  "dataset" : "VINIT",
  "userCode" : "SMMTEST",
  "payment" : null,
  "codeType" : null,
  "name" : "Sams Walmart",
  "payType" : "E",
  "taxability" : "Taxable/Exclude",
  "eemax" : "0.00",
  "ermax" : "-",
  "aggstatus" : "N/A",
  "limit" : null,
  "lmtfreq" : "0",
  "lmtfreqDisp" : "-",
  "eefreq" : "-",
  "eefreqDisp" : "-",
  "erfreq" : "-",
  "erfreqDisp" : "-",
  "aggRule1" : "0",
  "aggRule2" : "0",
  "effective" : null,
  "rescind" : null
}, {
  "dataset" : "VINIT",
  "userCode" : "GHHGHGH",
  "payment" : null,
  "codeType" : null,
  "name" : "SDFJSDJFSDJFJSD sdfSDJF SD F",
  "payType" : "E",
  "taxability" : "Limit-MTD",
  "eemax" : "67.00",
  "ermax" : "-",
  "aggstatus" : "N/A",
  "limit" : null,
  "lmtfreq" : "2",
  "lmtfreqDisp" : "-",
  "eefreq" : "-",
  "eefreqDisp" : "-",
  "erfreq" : "-",
  "erfreqDisp" : "-",
  "aggRule1" : "0",
  "aggRule2" : "0",
  "effective" : null,
  "rescind" : null
}, {
  "dataset" : "VINIT",
  "userCode" : "PAYME",
  "payment" : null,
  "codeType" : null,
  "name" : "sudhir pallapolu",
  "payType" : "E",
  "taxability" : "Taxable/Exclude",
  "eemax" : "0.00",
  "ermax" : "-",
  "aggstatus" : "N/A",
  "limit" : null,
  "lmtfreq" : "0",
  "lmtfreqDisp" : "-",
  "eefreq" : "-",
  "eefreqDisp" : "-",
  "erfreq" : "-",
  "erfreqDisp" : "-",
  "aggRule1" : "0",
  "aggRule2" : "0",
  "effective" : null,
  "rescind" : null
}, {
  "dataset" : "VINIT",
  "userCode" : "THIDID",
  "payment" : null,
  "codeType" : null,
  "name" : "Test BSI CO",
  "payType" : "E",
  "taxability" : "Limit-YTD",
  "eemax" : "1000.00",
  "ermax" : "-",
  "aggstatus" : "N/A",
  "limit" : null,
  "lmtfreq" : "0",
  "lmtfreqDisp" : "-",
  "eefreq" : "-",
  "eefreqDisp" : "-",
  "erfreq" : "-",
  "erfreqDisp" : "-",
  "aggRule1" : "0",
  "aggRule2" : "0",
  "effective" : null,
  "rescind" : null
}, {
  "dataset" : "VINIT",
  "userCode" : "TESTCO",
  "payment" : null,
  "codeType" : null,
  "name" : "Test CO Better than CostCo",
  "payType" : "E",
  "taxability" : "Taxable/Exclude",
  "eemax" : "0.00",
  "ermax" : "-",
  "aggstatus" : "N/A",
  "limit" : null,
  "lmtfreq" : "0",
  "lmtfreqDisp" : "-",
  "eefreq" : "-",
  "eefreqDisp" : "-",
  "erfreq" : "-",
  "erfreqDisp" : "-",
  "aggRule1" : "0",
  "aggRule2" : "0",
  "effective" : null,
  "rescind" : null
}, {
  "dataset" : "VINIT",
  "userCode" : "RYRYRY",
  "payment" : null,
  "codeType" : null,
  "name" : "THi sdfisdf",
  "payType" : "E",
  "taxability" : "Taxable/Exclude",
  "eemax" : "0.00",
  "ermax" : "-",
  "aggstatus" : "N/A",
  "limit" : null,
  "lmtfreq" : "0",
  "lmtfreqDisp" : "-",
  "eefreq" : "-",
  "eefreqDisp" : "-",
  "erfreq" : "-",
  "erfreqDisp" : "-",
  "aggRule1" : "0",
  "aggRule2" : "0",
  "effective" : null,
  "rescind" : null
}, {
  "dataset" : "VINIT",
  "userCode" : "TUTUTU",
  "payment" : null,
  "codeType" : null,
  "name" : "THIs fsdifsd fisd f",
  "payType" : "E",
  "taxability" : "Imputed",
  "eemax" : "99999999995.99",
  "ermax" : "-",
  "aggstatus" : "N/A",
  "limit" : null,
  "lmtfreq" : "0",
  "lmtfreqDisp" : "-",
  "eefreq" : "-",
  "eefreqDisp" : "-",
  "erfreq" : "-",
  "erfreqDisp" : "-",
  "aggRule1" : "0",
  "aggRule2" : "0",
  "effective" : null,
  "rescind" : null
}, {
  "dataset" : "VINIT",
  "userCode" : "TYTYTYT",
  "payment" : null,
  "codeType" : null,
  "name" : "This is CO",
  "payType" : "E",
  "taxability" : "Taxable/Exclude",
  "eemax" : "0.00",
  "ermax" : "-",
  "aggstatus" : "N/A",
  "limit" : null,
  "lmtfreq" : "0",
  "lmtfreqDisp" : "-",
  "eefreq" : "-",
  "eefreqDisp" : "-",
  "erfreq" : "-",
  "erfreqDisp" : "-",
  "aggRule1" : "0",
  "aggRule2" : "0",
  "effective" : null,
  "rescind" : null
}, {
  "dataset" : "VINIT",
  "userCode" : "MYCOMP",
  "payment" : null,
  "codeType" : null,
  "name" : "Win IT Inc",
  "payType" : "E",
  "taxability" : "Taxable/Exclude",
  "eemax" : "0.00",
  "ermax" : "-",
  "aggstatus" : "N/A",
  "limit" : null,
  "lmtfreq" : "0",
  "lmtfreqDisp" : "-",
  "eefreq" : "-",
  "eefreqDisp" : "-",
  "erfreq" : "-",
  "erfreqDisp" : "-",
  "aggRule1" : "0",
  "aggRule2" : "0",
  "effective" : null,
  "rescind" : null
}, {
  "dataset" : "VINIT",
  "userCode" : "YUYU",
  "payment" : null,
  "codeType" : null,
  "name" : "YUYU YUIYUI  YUYU dfjsdf",
  "payType" : "E",
  "taxability" : "Limit-QTD",
  "eemax" : "500.00",
  "ermax" : "-",
  "aggstatus" : "N/A",
  "limit" : null,
  "lmtfreq" : "1",
  "lmtfreqDisp" : "-",
  "eefreq" : "-",
  "eefreqDisp" : "-",
  "erfreq" : "-",
  "erfreqDisp" : "-",
  "aggRule1" : "0",
  "aggRule2" : "0",
  "effective" : null,
  "rescind" : null
} ]