[
    {
      "btxrate": null,
      "startDateDspl": "01/16/2020",
      "rescindDateDspl": "12/31/9999",
      "formulaTitle": null,
      "exprateDspl": "0.000000000",
      "maxwageDspl": "0.00",
      "taxType": "003",
      "formula": 1,
      "type": null,
      "county": null,
      "authCode": null,
      "monQuarTaxType": null,
      "companyCode": "TESTCOMP1",
      "taxCode": "BSI00000000",
      "acctNumber": "N/A",
      "bsiWage": "137700.00",
      "riskClass": "",
      "badRecord": 0
    },
    {
      "btxrate": null,
      "startDateDspl": "01/16/2020",
      "rescindDateDspl": "12/31/9999",
      "formulaTitle": null,
      "exprateDspl": "0.000000000",
      "maxwageDspl": "         0.00",
      "taxType": "010",
      "formula": 1,
      "type": null,
      "county": null,
      "authCode": null,
      "monQuarTaxType": null,
      "companyCode": "TESTCOMP1",
      "taxCode": "BSI00280000",
      "acctNumber": "N/A",
      "bsiWage": "14000.00",
      "riskClass": "",
      "badRecord": 0
    },
    {
      "btxrate": null,
      "startDateDspl": "01/01/2020",
      "rescindDateDspl": "12/31/9999",
      "formulaTitle": null,
      "exprateDspl": "0.000000000",
      "maxwageDspl": "         0.00",
      "taxType": "006",
      "formula": 1,
      "type": null,
      "county": null,
      "authCode": null,
      "monQuarTaxType": null,
      "companyCode": "TETS",
      "taxCode": "BSI00000000",
      "acctNumber": "N/A",
      "bsiWage": "0.00",
      "riskClass": "",
      "badRecord": 0
    },
    {
      "btxrate": null,
      "startDateDspl": "01/17/2020",
      "rescindDateDspl": "12/31/9999",
      "formulaTitle": null,
      "exprateDspl": "0.000000000",
      "maxwageDspl": "         0.00",
      "taxType": "010",
      "formula": 2,
      "type": null,
      "county": null,
      "authCode": null,
      "monQuarTaxType": null,
      "companyCode": "TETS",
      "taxCode": "BSI00000000",
      "acctNumber": "N/A",
      "bsiWage": "1655.00",
      "riskClass": "",
      "badRecord": 0
    }
  ]